airflow_exporter/__init__.py
airflow_exporter/prometheus_exporter.py
airflow_exporter-1.6.0.dist-info/licenses/LICENSE
airflow_exporter-1.6.0.dist-info/METADATA
airflow_exporter-1.6.0.dist-info/WHEEL
airflow_exporter-1.6.0.dist-info/entry_points.txt
airflow_exporter-1.6.0.dist-info/top_level.txt
airflow_exporter-1.6.0.dist-info/RECORD
