Metadata-Version: 2.4
Name: airflow-exporter
Version: 1.6.0
Summary: Airflow plugin to export dag and task based metrics to Prometheus.
Home-page: https://github.com/epoch8/airflow-exporter
Keywords: airflow plugin prometheus exporter metrics
Classifier: Environment :: Web Environment
Classifier: Intended Audience :: System Administrators
Classifier: Natural Language :: English
Classifier: Operating System :: OS Independent
Classifier: Programming Language :: Python
Classifier: Programming Language :: Python :: 2
Classifier: Programming Language :: Python :: 3
Classifier: Topic :: System :: Monitoring
License-File: LICENSE
Requires-Dist: apache-airflow>=2.0.0
Requires-Dist: prometheus_client>=0.4.2
Requires-Dist: packaging
Dynamic: classifier
Dynamic: description
Dynamic: description-content-type
Dynamic: home-page
Dynamic: keywords
Dynamic: license-file
Dynamic: requires-dist
Dynamic: summary
